mathew/__init__.py
mathew/constants.py
mathew/helper.py
mathew/linalg.py
mathew/prime.py
mathew-0.0.4.dist-info/LICENSE
mathew-0.0.4.dist-info/METADATA
mathew-0.0.4.dist-info/WHEEL
mathew-0.0.4.dist-info/top_level.txt
mathew-0.0.4.dist-info/RECORD
