Metadata-Version: 2.1
Name: mathew
Version: 0.0.4
Summary: My personal math lib
Home-page: https://github.com/larsvommars/mathew
Author: LarsVomMars
Author-email: dev@kroenner.eu
License: MIT
Platform: UNKNOWN
